{
  "project_info": {
    "project_number": "738558732821",
    "firebase_url": "https://autowork-44239.firebaseio.com",
    "project_id": "autowork-44239",
    "storage_bucket": "autowork-44239.appspot.com"
  },
  "client": [
    {
      "client_info": {
        "mobilesdk_app_id": "1:738558732821:android:458c8f49bdb638eab8bc1c",
        "android_client_info": {
          "package_name": "com.example.autowork"
        }
      },
      "oauth_client": [
        {
          "client_id": "738558732821-5ofgp20d3gq6m1ra6c7uvjth2dgelo89.apps.googleusercontent.com",
          "client_type": 1,
          "android_info": {
            "package_name": "com.example.autowork",
            "certificate_hash": "01734a251b2bd96e854b1953803494453924a346"
          }
        },
        {
          "client_id": "738558732821-asraube1vfho4utcpspb2h1mlo96ifca.apps.googleusercontent.com",
          "client_type": 3
        }
      ],
      "api_key": [
        {
          "current_key": "AIzaSyDciJEuRlUBjV_MOOqBqpX_cP-EM0qZ1tQ"
        }
      ],
      "services": {
        "appinvite_service": {
          "other_platform_oauth_client": [
            {
              "client_id": "738558732821-asraube1vfho4utcpspb2h1mlo96ifca.apps.googleusercontent.com",
              "client_type": 3
            }
          ]
        }
      }
    }
  ],
  "configuration_version": "1"
}